Metadata-Version: 2.4
Name: InvokeAI
Version: 6.11.0
Summary: A full-featured AI-assisted image generation environment designed for creatives and enthusiasts.
Author-email: Invoke <support@invoke.ai>
License:                                  Apache License
Project-URL: Homepage, https://invoke-ai.github.io/InvokeAI/
Project-URL: Documentation, https://invoke-ai.github.io/InvokeAI/
Project-URL: Source, https://github.com/invoke-ai/InvokeAI/
Project-URL: Bug Reports, https://github.com/invoke-ai/InvokeAI/issues
Project-URL: Discord, https://discord.gg/ZmtBAhwWhy
Keywords: stable-diffusion,AI
Classifier: Development Status :: 5 - Production/Stable
Classifier: Environment :: GPU
Classifier: Environment :: GPU :: NVIDIA CUDA
Classifier: Environment :: MacOS X
Classifier: Intended Audience :: End Users/Desktop
Classifier: Intended Audience :: Developers
Classifier: License :: OSI Approved :: Apache Software License
Classifier: Operating System :: POSIX :: Linux
Classifier: Operating System :: MacOS
Classifier: Operating System :: Microsoft :: Windows
Classifier: Programming Language :: Python :: 3 :: Only
Classifier: Programming Language :: Python :: 3.12
Classifier: Topic :: Artistic Software
Classifier: Topic :: Internet :: WWW/HTTP :: WSGI :: Application
Classifier: Topic :: Internet :: WWW/HTTP :: WSGI :: Server
Classifier: Topic :: Multimedia :: Graphics
Classifier: Topic :: Scientific/Engineering :: Artificial Intelligence
Classifier: Topic :: Scientific/Engineering :: Image Processing
Requires-Python: <3.13,>=3.11
License-File: LICENSE
License-File: LICENSE-SD1+SD2.txt
License-File: LICENSE-SDXL.txt
Requires-Dist: accelerate
Requires-Dist: bitsandbytes; sys_platform != "darwin"
Requires-Dist: compel==2.1.1
Requires-Dist: diffusers[torch]==0.36.0
Requires-Dist: gguf
Requires-Dist: mediapipe==0.10.14
Requires-Dist: numpy<2.0.0
Requires-Dist: onnx==1.16.1
Requires-Dist: onnxruntime==1.19.2
Requires-Dist: opencv-contrib-python
Requires-Dist: safetensors
Requires-Dist: sentencepiece==0.2.0
Requires-Dist: spandrel
Requires-Dist: torch~=2.7.0
Requires-Dist: torchsde
Requires-Dist: torchvision
Requires-Dist: transformers>=4.56.0
Requires-Dist: fastapi-events
Requires-Dist: fastapi==0.118.3
Requires-Dist: huggingface-hub
Requires-Dist: pydantic-settings
Requires-Dist: pydantic
Requires-Dist: python-socketio
Requires-Dist: uvicorn[standard]
Requires-Dist: blake3
Requires-Dist: Deprecated
Requires-Dist: dnspython
Requires-Dist: dynamicprompts
Requires-Dist: einops
Requires-Dist: picklescan
Requires-Dist: pillow
Requires-Dist: prompt-toolkit
Requires-Dist: pypatchmatch
Requires-Dist: python-multipart
Requires-Dist: requests
Requires-Dist: semver~=3.0.1
Requires-Dist: PyWavelets
Provides-Extra: xformers
Requires-Dist: xformers>=0.0.28.post1; sys_platform != "darwin" and extra == "xformers"
Provides-Extra: cpu
Requires-Dist: torch==2.7.1+cpu; extra == "cpu"
Requires-Dist: torchvision==0.22.1+cpu; extra == "cpu"
Provides-Extra: cuda
Requires-Dist: torch==2.7.1+cu128; extra == "cuda"
Requires-Dist: torchvision==0.22.1+cu128; extra == "cuda"
Provides-Extra: rocm
Requires-Dist: torch==2.7.1+rocm6.3; extra == "rocm"
Requires-Dist: torchvision==0.22.1+rocm6.3; extra == "rocm"
Requires-Dist: pytorch-triton-rocm; extra == "rocm"
Provides-Extra: onnx
Requires-Dist: onnxruntime; extra == "onnx"
Provides-Extra: onnx-cuda
Requires-Dist: onnxruntime-gpu; extra == "onnx-cuda"
Provides-Extra: onnx-directml
Requires-Dist: onnxruntime-directml; extra == "onnx-directml"
Provides-Extra: dist
Requires-Dist: pip-tools; extra == "dist"
Requires-Dist: pipdeptree; extra == "dist"
Requires-Dist: twine; extra == "dist"
Provides-Extra: docs
Requires-Dist: mkdocs-material>=9.5.36; extra == "docs"
Requires-Dist: mkdocs-git-revision-date-localized-plugin; extra == "docs"
Requires-Dist: mkdocs-redirects; extra == "docs"
Requires-Dist: mkdocstrings[python]>=0.26.1; extra == "docs"
Provides-Extra: dev
Requires-Dist: jurigged; extra == "dev"
Requires-Dist: pudb; extra == "dev"
Requires-Dist: snakeviz; extra == "dev"
Requires-Dist: gprof2dot; extra == "dev"
Provides-Extra: test
Requires-Dist: ruff~=0.11.2; extra == "test"
Requires-Dist: ruff-lsp~=0.0.62; extra == "test"
Requires-Dist: mypy; extra == "test"
Requires-Dist: pre-commit; extra == "test"
Requires-Dist: pytest>6.0.0; extra == "test"
Requires-Dist: pytest-cov; extra == "test"
Requires-Dist: pytest-timeout; extra == "test"
Requires-Dist: pytest-datadir; extra == "test"
Requires-Dist: requests_testadapter; extra == "test"
Requires-Dist: httpx; extra == "test"
Requires-Dist: polyfactory==2.19.0; extra == "test"
Requires-Dist: humanize==4.12.1; extra == "test"
Dynamic: license-file
